{"duration": 0.1421365737915039, "input_args": {"transformer": "TransformerWrapper(include=['latitude', 'longitude', 'cbd_dist', 'min_dist_mrt', 'remaining_lease', 'floor_area_sqm'],\n                   transformer=SimpleImputer())", "X": "        flat_type storey_range  floor_area_sqm      flat_model  ...      cbd_dist  min_dist_mrt  remaining_lease   region\n160550     4 ROOM     07 TO 09            90.0        Model A2  ...  18065.523438    445.128784               77     WEST\n79843      4 ROOM     07 TO 09           101.0         Model A  ...   3723.635986    708.182983               77    SOUTH\n92783   EXECUTIVE     07 TO 09           144.0      Maisonette  ...  18062.152344    326.570312               78    NORTH\n187843     3 ROOM     04 TO 06            67.0  New Generation  ...  14031.692383    929.200989               61     WEST\n63534      5 ROOM     34 TO 36           117.0            DBSS  ...   5974.384766    440.972351               93  CENTRAL\n...           ...          ...             ...             ...  ...           ...           ...              ...      ...\n119906     2 ROOM     07 TO 09            47.0         Model A  ...  14493.895508   1589.125122               95    SOUTH\n192476     4 ROOM     10 TO 12           101.0         Model A  ...  17894.740234    412.462524               74    NORTH\n17730      5 ROOM     01 TO 03           135.0         Model A  ...  14678.268555    999.789062               80    SOUTH\n28030      3 ROOM     07 TO 09            76.0        Improved  ...   3360.788086   1108.692139               58     EAST\n15725      4 ROOM     10 TO 12            91.0         Model A  ...  19220.257812    592.253662               85    NORTH\n\n[139853 rows x 10 columns]", "y": "160550    13.021438\n79843     13.279367\n92783     13.253391\n187843    12.736701\n63534     13.721200\n            ...    \n119906    12.439166\n192476    13.136267\n17730     13.049792\n28030     12.847926\n15725     12.765689\nName: log_resale_price, Length: 139853, dtype: float32", "message": "None", "**": "{}"}}